[
    {
        "_id": "63491c0d734c2488435a0927",
        "price": "$1,715.04",
        "name": "Laurie House",
        "gender": "female",
        "company": "MEDCOM",
        "email": "lauriehouse@medcom.com"
    },
    {
        "_id": "63491c0d42232614c5688d10",
        "price": "$1,224.31",
        "name": "Tracy Burton",
        "gender": "female",
        "company": "ACCEL",
        "email": "tracyburton@accel.com"
    },
    {
        "_id": "63491c0d299cb675f2a8d7ee",
        "price": "$3,488.86",
        "name": "Noble Berg",
        "gender": "male",
        "company": "COMBOGEN",
        "email": "nobleberg@combogen.com"
    },
    {
        "_id": "63491c0d2821c9210e18b317",
        "price": "$2,215.31",
        "name": "Dale Flores",
        "gender": "male",
        "company": "AQUAFIRE",
        "email": "daleflores@aquafire.com"
    },
    {
        "_id": "63491c0d60a0a4a2ad2af1e1",
        "price": "$1,126.40",
        "name": "Beulah Vazquez",
        "gender": "female",
        "company": "COMTOUR",
        "email": "beulahvazquez@comtour.com"
    },
    {
        "_id": "63491c0dfe7a4ec083ea7432",
        "price": "$2,204.45",
        "name": "Phillips Malone",
        "gender": "male",
        "company": "OVERPLEX",
        "email": "phillipsmalone@overplex.com"
    },
    {
        "_id": "63491c0d85cb2dd0139718f5",
        "price": "$2,559.39",
        "name": "Rose Howard",
        "gender": "female",
        "company": "FLYBOYZ",
        "email": "rosehoward@flyboyz.com"
    },
    {
        "_id": "63491c0de0355f47bcfaa529",
        "price": "$1,811.36",
        "name": "Knight Sharpe",
        "gender": "male",
        "company": "QUONATA",
        "email": "knightsharpe@quonata.com"
    },
    {
        "_id": "63491c0dee74b1160128b8ed",
        "price": "$2,576.87",
        "name": "Emma Patel",
        "gender": "female",
        "company": "IZZBY",
        "email": "emmapatel@izzby.com"
    },
    {
        "_id": "63491c0d522c4f239a468e99",
        "price": "$1,728.15",
        "name": "Shauna Caldwell",
        "gender": "female",
        "company": "MAINELAND",
        "email": "shaunacaldwell@maineland.com"
    },
    {
        "_id": "63491c0d484de8efd619d8e3",
        "price": "$3,019.74",
        "name": "Dina Graves",
        "gender": "female",
        "company": "FILODYNE",
        "email": "dinagraves@filodyne.com"
    },
    {
        "_id": "63491c0d1b7b3cd1090f099b",
        "price": "$3,840.56",
        "name": "Sharpe Gregory",
        "gender": "male",
        "company": "BUZZOPIA",
        "email": "sharpegregory@buzzopia.com"
    },
    {
        "_id": "63491c0de54b905fc2088360",
        "price": "$3,992.21",
        "name": "Levy Brock",
        "gender": "male",
        "company": "IMANT",
        "email": "levybrock@imant.com"
    },
    {
        "_id": "63491c0db6dca32745e13e35",
        "price": "$2,679.78",
        "name": "Waters Robertson",
        "gender": "male",
        "company": "ZAGGLE",
        "email": "watersrobertson@zaggle.com"
    },
    {
        "_id": "63491c0d047c26ddbd25b2f3",
        "price": "$3,226.90",
        "name": "Latisha Copeland",
        "gender": "female",
        "company": "HARMONEY",
        "email": "latishacopeland@harmoney.com"
    },
    {
        "_id": "63491c0dcce26b609bebd4a8",
        "price": "$3,183.10",
        "name": "Kendra Beard",
        "gender": "female",
        "company": "SNIPS",
        "email": "kendrabeard@snips.com"
    },
    {
        "_id": "63491c0d8ffa2599f99b537c",
        "price": "$1,469.02",
        "name": "Bessie Hodge",
        "gender": "female",
        "company": "ZORK",
        "email": "bessiehodge@zork.com"
    },
    {
        "_id": "63491c0db3607aa92e4d25e6",
        "price": "$1,904.79",
        "name": "Jeanine Terry",
        "gender": "female",
        "company": "COMCUR",
        "email": "jeanineterry@comcur.com"
    },
    {
        "_id": "63491c0dae2d5d1aa5784692",
        "price": "$1,282.46",
        "name": "Rosetta Pearson",
        "gender": "female",
        "company": "VIDTO",
        "email": "rosettapearson@vidto.com"
    },
    {
        "_id": "63491c0dadcb54ebb0eb42ef",
        "price": "$1,322.20",
        "name": "Kristy Douglas",
        "gender": "female",
        "company": "GENMOM",
        "email": "kristydouglas@genmom.com"
    },
    {
        "_id": "63491c0dbbffa008562868b4",
        "price": "$3,374.44",
        "name": "Maura Melendez",
        "gender": "female",
        "company": "ZBOO",
        "email": "mauramelendez@zboo.com"
    },
    {
        "_id": "63491c0d13760e4e3f9032fd",
        "price": "$1,699.93",
        "name": "Dickson Kidd",
        "gender": "male",
        "company": "RONBERT",
        "email": "dicksonkidd@ronbert.com"
    },
    {
        "_id": "63491c0d814027861dfeb2ce",
        "price": "$1,556.56",
        "name": "Lisa Phillips",
        "gender": "female",
        "company": "MARQET",
        "email": "lisaphillips@marqet.com"
    },
    {
        "_id": "63491c0d652cce6ebbad5c2b",
        "price": "$2,466.28",
        "name": "Macdonald Travis",
        "gender": "male",
        "company": "EXOTERIC",
        "email": "macdonaldtravis@exoteric.com"
    },
    {
        "_id": "63491c0dcad12488e6b030ea",
        "price": "$2,511.87",
        "name": "Day Wallace",
        "gender": "male",
        "company": "ZAJ",
        "email": "daywallace@zaj.com"
    },
    {
        "_id": "63491c0d4ef8dafa8c55bf02",
        "price": "$2,241.81",
        "name": "Louisa Brown",
        "gender": "female",
        "company": "MUSAPHICS",
        "email": "louisabrown@musaphics.com"
    },
    {
        "_id": "63491c0daac515f8c8ae8bd1",
        "price": "$2,718.37",
        "name": "Chase Parrish",
        "gender": "male",
        "company": "SUREPLEX",
        "email": "chaseparrish@sureplex.com"
    },
    {
        "_id": "63491c0d19b03a262ba46687",
        "price": "$3,130.18",
        "name": "Welch Kelley",
        "gender": "male",
        "company": "COMTENT",
        "email": "welchkelley@comtent.com"
    },
    {
        "_id": "63491c0df45099d6119876f6",
        "price": "$3,697.06",
        "name": "Morgan Bridges",
        "gender": "female",
        "company": "ELITA",
        "email": "morganbridges@elita.com"
    },
    {
        "_id": "63491c0deb7613e1c84f88de",
        "price": "$2,416.18",
        "name": "Tina Sharp",
        "gender": "female",
        "company": "LOVEPAD",
        "email": "tinasharp@lovepad.com"
    },
    {
        "_id": "63491c0db7dba11c69ecb534",
        "price": "$1,036.26",
        "name": "Gena Ware",
        "gender": "female",
        "company": "FUELTON",
        "email": "genaware@fuelton.com"
    },
    {
        "_id": "63491c0d3866bdf599534bb1",
        "price": "$3,303.54",
        "name": "Christa Rivera",
        "gender": "female",
        "company": "CINESANCT",
        "email": "christarivera@cinesanct.com"
    }
]